pytest_sqlalchemy_mock/__init__.py
pytest_sqlalchemy_mock/base.py
pytest_sqlalchemy_mock/model_mocker.py
pytest_sqlalchemy_mock-0.1.7.dist-info/LICENSE
pytest_sqlalchemy_mock-0.1.7.dist-info/METADATA
pytest_sqlalchemy_mock-0.1.7.dist-info/WHEEL
pytest_sqlalchemy_mock-0.1.7.dist-info/entry_points.txt
pytest_sqlalchemy_mock-0.1.7.dist-info/top_level.txt
pytest_sqlalchemy_mock-0.1.7.dist-info/RECORD
