Metadata-Version: 2.1
Name: pytest-sqlalchemy-mock
Version: 0.1.7
Summary: pytest sqlalchemy plugin for mock
Author-email: Resul Yurttakalan <resulyrt93@gmail.com>
License: MIT License
Project-URL: Homepage, https://github.com/resulyrt93/pytest-sqlalchemy-mock
Classifier: Framework :: Pytest
Classifier: Development Status :: 3 - Alpha
Classifier: Topic :: Software Development :: Testing
Classifier: Intended Audience :: Developers
Classifier: Operating System :: OS Independent
Classifier: Programming Language :: Python :: 3.9
Classifier: Programming Language :: Python :: 3.10
Classifier: Programming Language :: Python :: 3.11
Classifier: Programming Language :: Python :: 3.12
Classifier: License :: OSI Approved :: MIT License
Requires-Python: >=3.9
License-File: LICENSE
Requires-Dist: pytest>=7.0.0
Requires-Dist: sqlalchemy>=2.0.6
Provides-Extra: dev
Requires-Dist: black>=23.12.1; extra == "dev"
Requires-Dist: build>=1.0.3; extra == "dev"
Requires-Dist: flake8>=7.0.0; extra == "dev"
Requires-Dist: isort>=5.13.2; extra == "dev"
Requires-Dist: pre-commit>=3.6.0; extra == "dev"
Requires-Dist: pytest-cov>=4.1.0; extra == "dev"
